topsis/102083043.py
topsis_Anant_102083043-1.0.0.dist-info/LICENSE
topsis_Anant_102083043-1.0.0.dist-info/METADATA
topsis_Anant_102083043-1.0.0.dist-info/WHEEL
topsis_Anant_102083043-1.0.0.dist-info/top_level.txt
topsis_Anant_102083043-1.0.0.dist-info/RECORD
