Metadata-Version: 2.1
Name: topsis-Anant-102083043
Version: 1.0.0
Summary: Multiple criteria decision making (MCDM) using TOPSIS
Author: Anant Joshi
Author-email: ajoshi_be19@thapar.edu
License: MIT
Platform: UNKNOWN
Classifier: License :: OSI Approved :: MIT License
Classifier: Programming Language :: Python :: 3.6
Classifier: Programming Language :: Python :: 3.7
Classifier: Programming Language :: Python :: 3.8
Classifier: Programming Language :: Python :: 3.9
License-File: LICENSE
